generate_iconset/__init__.py
generate_iconset/generate_iconset.py
generate_iconset/version.py
generate_iconset-1.2.0.dist-info/LICENSE
generate_iconset-1.2.0.dist-info/METADATA
generate_iconset-1.2.0.dist-info/WHEEL
generate_iconset-1.2.0.dist-info/entry_points.txt
generate_iconset-1.2.0.dist-info/top_level.txt
generate_iconset-1.2.0.dist-info/RECORD
