Metadata-Version: 2.1
Name: generate-iconset
Version: 1.2.0
Summary: Generating an iconset for Mac OS application
Home-page: https://github.com/retifrav/generate-iconset
Author: retif
License: UNKNOWN
Project-URL: Bug Tracker, https://github.com/retifrav/generate-iconset/issues
Keywords: iconutil,iconset
Platform: UNKNOWN
Classifier: Programming Language :: Python :: 3.7
Classifier: License :: OSI Approved :: GNU General Public License v3 (GPLv3)
Classifier: Operating System :: MacOS
Classifier: Environment :: Console
Classifier: Intended Audience :: Developers
Classifier: Topic :: Multimedia :: Graphics :: Graphics Conversion
Requires-Python: >=3.7
License-File: LICENSE
